listdiff/__init__.py
listdiff/py.typed
listdiff-1.0.5.dist-info/METADATA
listdiff-1.0.5.dist-info/WHEEL
listdiff-1.0.5.dist-info/licenses/LICENSE
listdiff-1.0.5.dist-info/RECORD
