Metadata-Version: 2.4
Name: listdiff
Version: 1.0.5
Summary: Diff 2 python lists using a given key
Project-URL: Homepage, https://github.com/rkhwaja/pylistdiff
Maintainer-email: Rehan Khwaja <rehan@khwaja.name>
License-Expression: MIT
License-File: LICENSE
Classifier: Development Status :: 5 - Production/Stable
Classifier: Intended Audience :: Developers
Classifier: Programming Language :: Python :: 3.8
Classifier: Programming Language :: Python :: 3.9
Classifier: Programming Language :: Python :: 3.10
Classifier: Programming Language :: Python :: 3.11
Classifier: Programming Language :: Python :: 3.12
Classifier: Programming Language :: Python :: 3.13
Classifier: Programming Language :: Python :: 3.14
Requires-Python: >=3.8
Requires-Dist: typing-extensions>=4.13.2
